GenwoxueSpringXilie/README.md
GenwoxueSpringXilie/__init__.py
GenwoxueSpringXilie/__main__.py
GenwoxueSpringXilie/file.epub
GenwoxueSpringXilie/index.html
GenwoxueSpringXilie/css/__init__.py
GenwoxueSpringXilie/css/annotations.css
GenwoxueSpringXilie/css/main.css
GenwoxueSpringXilie/css/normalize.css
GenwoxueSpringXilie/css/popup.css
GenwoxueSpringXilie/font/__init__.py
GenwoxueSpringXilie/font/fontello.eot
GenwoxueSpringXilie/font/fontello.svg
GenwoxueSpringXilie/font/fontello.ttf
GenwoxueSpringXilie/font/fontello.woff
GenwoxueSpringXilie/img/__init__.py
GenwoxueSpringXilie/img/annotator-glyph-sprite.png
GenwoxueSpringXilie/img/annotator-icon-sprite.png
GenwoxueSpringXilie/img/apple-touch-icon.png
GenwoxueSpringXilie/img/cancelfullscreen.png
GenwoxueSpringXilie/img/close.png
GenwoxueSpringXilie/img/fullscreen.png
GenwoxueSpringXilie/img/loader.gif
GenwoxueSpringXilie/img/menu-icon.png
GenwoxueSpringXilie/img/save.png
GenwoxueSpringXilie/img/saved.png
GenwoxueSpringXilie/img/settings-s.png
GenwoxueSpringXilie/img/settings.png
GenwoxueSpringXilie/img/star.png
GenwoxueSpringXilie/js/__init__.py
GenwoxueSpringXilie/js/epub.js
GenwoxueSpringXilie/js/epub.min.js
GenwoxueSpringXilie/js/epub.min.map
GenwoxueSpringXilie/js/hooks.min.js
GenwoxueSpringXilie/js/hooks.min.map
GenwoxueSpringXilie/js/reader.js
GenwoxueSpringXilie/js/reader.js.map
GenwoxueSpringXilie/js/reader.min.js
GenwoxueSpringXilie/js/reader.min.map
GenwoxueSpringXilie/js/hooks/__init__.py
GenwoxueSpringXilie/js/hooks/extensions/__init__.py
GenwoxueSpringXilie/js/hooks/extensions/highlight.js
GenwoxueSpringXilie/js/libs/__init__.py
GenwoxueSpringXilie/js/libs/jquery.min.js
GenwoxueSpringXilie/js/libs/localforage.min.js
GenwoxueSpringXilie/js/libs/screenfull.js
GenwoxueSpringXilie/js/libs/screenfull.min.js
GenwoxueSpringXilie/js/libs/zip.min.js
GenwoxueSpringXilie/js/plugins/__init__.py
GenwoxueSpringXilie/js/plugins/hypothesis.js
GenwoxueSpringXilie/js/plugins/search.js
genwoxue_spring_xilie-2024.3.2.0.dist-info/METADATA
genwoxue_spring_xilie-2024.3.2.0.dist-info/WHEEL
genwoxue_spring_xilie-2024.3.2.0.dist-info/entry_points.txt
genwoxue_spring_xilie-2024.3.2.0.dist-info/top_level.txt
genwoxue_spring_xilie-2024.3.2.0.dist-info/RECORD
